myprac/__init__.py
myprac/prac1.py
myprac/prac2.py
myprac/prac3.py
myprac/prac4.py
myprac/prac5.py
myprac-1.0.0.dist-info/METADATA
myprac-1.0.0.dist-info/WHEEL
myprac-1.0.0.dist-info/top_level.txt
myprac-1.0.0.dist-info/RECORD
