Metadata-Version: 2.4
Name: myprac
Version: 1.0.0
Summary: A Python library containing 5 AI & DS practical programs.
Author: Mine
Author-email: your_email@example.com
Requires-Python: >=3.8
Dynamic: author
Dynamic: author-email
Dynamic: description
Dynamic: description-content-type
Dynamic: requires-python
Dynamic: summary
